octus/__init__.py
octus/core.py
octus/loaders.py
octus-0.1.3.dist-info/licenses/LICENSE
octus-0.1.3.dist-info/METADATA
octus-0.1.3.dist-info/WHEEL
octus-0.1.3.dist-info/top_level.txt
octus-0.1.3.dist-info/RECORD
