Metadata-Version: 2.4
Name: octus
Version: 0.1.3
Summary: A Python package designed to simplify configuration management for applications. It allows you to load configurations from YAML files, with support for environment-specific overrides and Pydantic for schema validation.
Author-email: Nuriakhmetov Timur <dinoartuso@ya.ru>
License-Expression: MIT
Project-URL: Homepage, https://github.com/artuso/octus
Project-URL: Bug Tracker, https://github.com/artuso/octus/issues
Classifier: Programming Language :: Python :: 3
Classifier: Operating System :: OS Independent
Requires-Python: >=3.11
License-File: LICENSE
Requires-Dist: pydantic==2.12.0
Requires-Dist: pyyaml==6.0.3
Provides-Extra: dev
Requires-Dist: pytest==8.4.2; extra == "dev"
Requires-Dist: build>=1.3.0; extra == "dev"
Requires-Dist: twine>=6.2.0; extra == "dev"
Dynamic: license-file
